<?xml version="1.0" encoding="utf-8"?>
<data>
	<segment>
		<start>0.11</start>
		<end>2.16</end>
		<speaker>A</speaker>
		<speaker_label>ATCO Ground</speaker_label>
		<text>[#callsign]Hotel[/#callsign] [#callsign]Echo[/#callsign] [#callsign]X-ray[/#callsign] [#value]number[/#value] [#value]one[/#value] [#command]report[/#command] [#value]final[/#value]</text>
		<tags>
			<correct>0</correct>
			<correct_transcript>1</correct_transcript>
			<correct_tagging>0</correct_tagging>
			<non_english>0</non_english>
		</tags>
	</segment>
	<segment>
		<start>2.25</start>
		<end>5.23</end>
		<speaker>B</speaker>
		<speaker_label></speaker_label>
		<text>[#value]number[/#value] [#value]one[/#value] [#command]report[/#command] [#value]final[/#value] [#callsign]Hotel[/#callsign] [#callsign]Echo[/#callsign] [#callsign]X-ray[/#callsign]</text>
		<tags>
			<correct>0</correct>
			<correct_transcript>1</correct_transcript>
			<correct_tagging>0</correct_tagging>
			<non_english>0</non_english>
		</tags>
	</segment>
</data>
